pyarmor_runtime_001219/pyarmor_runtime.so
pyarmor_runtime_001219/__init__.py
eff/package_info.py
eff/__init__.py
eff/callbacks/__init__.py
eff/callbacks/content_callbacks.py
eff/callbacks/callback_registry.py
eff/callbacks/key_callbacks.py
eff/cookbooks/__init__.py
eff/cookbooks/dict_cookbook.py
eff/cookbooks/vocabulary_cookbook.py
eff/validator/__init__.py
eff/validator/conditions.py
eff/validator/validator.py
eff/core/archive.py
eff/core/__init__.py
eff/core/artifact.py
eff/core/file.py
eff/core/codec.py
eff/core/memory.py
eff/core/cookbook.py
eff/core/artifact_registry.py
eff/core/metadata.py
eff/utils/log_level.py
eff/utils/__init__.py
eff/utils/deprecated.py
eff/utils/pretty.py
eff/utils/object_class.py
eff/codec/__init__.py
eff/codec/checksum.py
eff/codec/zero_codec.py
eff/scripts/__init__.py
eff/scripts/eff_inspect.py
eff/scripts/generate_tokens.py
eff/scripts/eff_recrypt.py
nvidia_eff-0.6.7.dist-info/RECORD
nvidia_eff-0.6.7.dist-info/WHEEL
nvidia_eff-0.6.7.dist-info/entry_points.txt
nvidia_eff-0.6.7.dist-info/METADATA
nvidia_eff-0.6.7.dist-info/LICENSE.txt
nvidia_eff-0.6.7.dist-info/top_level.txt
