Metadata-Version: 2.1
Name: nvidia-eff
Version: 0.6.7
Summary: NVIDIA Exchange File Format
Author: Tomasz Kornuta, Varun Praveen
Author-email: tkornuta@nvidia.com, vpraveen@nvidia.com
Maintainer: Tomasz Kornuta, Varun Praveen
Maintainer-email: tkornuta@nvidia.com, vpraveen@nvidia.com
License: NVIDIA Proprietary Software
Keywords: nvidia,eff,archive
Classifier: Development Status :: 5 - Production/Stable
Classifier: Intended Audience :: Developers
Classifier: Intended Audience :: Information Technology
Classifier: Topic :: Software Development :: Libraries
Classifier: Topic :: Software Development :: Libraries :: Python Modules
Classifier: Topic :: Utilities
Classifier: License :: Other/Proprietary License
Classifier: Programming Language :: Python :: 3.8
Classifier: Environment :: Console
Classifier: Natural Language :: English
Classifier: Operating System :: OS Independent
Requires-Python: ==3.8.*
License-File: LICENSE.txt
Requires-Dist: ruamel.yaml
Requires-Dist: pyarmor==8.5.8
Requires-Dist: pyinstaller
Requires-Dist: wrapt
Requires-Dist: isort[requirements]<5
Requires-Dist: black==22.3.0; python_version < "3.10"
Requires-Dist: dataclasses; python_version == "3.6"
Requires-Dist: black<26.0.0,>24.3; python_version >= "3.10"
Provides-Extra: all
Requires-Dist: pytest; extra == "all"
Requires-Dist: pytest-runner; extra == "all"
Requires-Dist: sphinx>=3.0; extra == "all"
Requires-Dist: sphinx-rtd-theme; extra == "all"
Requires-Dist: sphinxcontrib-bibtex; extra == "all"
Requires-Dist: numpy; extra == "all"
Requires-Dist: keras==2.2.5; extra == "all"
Requires-Dist: tensorflow-gpu==1.15.5; extra == "all"
Requires-Dist: nvidia-eff-tao-encryption; extra == "all"
Provides-Extra: docs
Requires-Dist: sphinx>=3.0; extra == "docs"
Requires-Dist: sphinx-rtd-theme; extra == "docs"
Requires-Dist: sphinxcontrib-bibtex; extra == "docs"
Provides-Extra: keras
Requires-Dist: numpy; extra == "keras"
Requires-Dist: keras==2.2.5; extra == "keras"
Requires-Dist: tensorflow-gpu==1.15.5; extra == "keras"
Provides-Extra: tao_encryption
Requires-Dist: nvidia-eff-tao-encryption; extra == "tao-encryption"
Provides-Extra: test
Requires-Dist: pytest; extra == "test"
Requires-Dist: pytest-runner; extra == "test"
